setup.py
adt/__init__.py
adt/adt.py
adt/f.py
adt.py.egg-info/PKG-INFO
adt.py.egg-info/SOURCES.txt
adt.py.egg-info/dependency_links.txt
adt.py.egg-info/top_level.txt